README.md
flask_mix.py
setup.py
Flask_Mix.egg-info/PKG-INFO
Flask_Mix.egg-info/SOURCES.txt
Flask_Mix.egg-info/dependency_links.txt
Flask_Mix.egg-info/not-zip-safe
Flask_Mix.egg-info/requires.txt
Flask_Mix.egg-info/top_level.txt