Metadata-Version: 2.1
Name: Flask-Mix
Version: 0.0.2
Summary: Integrates Laravel Mix with Flask
Home-page: https://github.com/knicklabs/flask-mix
Author: Nickolas Kenyeres
Author-email: nickolas@knicklabs.com
License: MIT
Keywords: flask,webpack,assets,static,laravel,mix
Platform: any
Classifier: Environment :: Web Environment
Classifier: Intended Audience :: Developers
Classifier: License :: OSI Approved :: MIT License
Classifier: Operating System :: OS Independent
Classifier: Programming Language :: Python
Classifier: Framework :: Flask
Classifier: Topic :: Internet :: WWW/HTTP :: Dynamic Content
Classifier: Topic :: Software Development :: Libraries :: Python Modules
Requires-Python: >=3.6
